litemcp/__init__.py
litemcp/agent_sdk.py
litemcp/config.py
litemcp/lanchain_sdk.py
litemcp/manager.py
litemcp/server.py
litemcp-0.1.1.dist-info/LICENSE
litemcp-0.1.1.dist-info/METADATA
litemcp-0.1.1.dist-info/WHEEL
litemcp-0.1.1.dist-info/RECORD
