Metadata-Version: 2.3
Name: litemcp
Version: 0.1.1
Summary: A minimal, lightweight client designed to simplify SDK (e.g., LangChain, Agent SDK) adoption into MCP.
Author: myan
Author-email: myan@redhat.com
Requires-Python: >=3.11,<4.0
Classifier: Programming Language :: Python :: 3
Classifier: Programming Language :: Python :: 3.11
Classifier: Programming Language :: Python :: 3.12
Classifier: Programming Language :: Python :: 3.13
Requires-Dist: commentjson (>=0.9.0,<0.10.0)
Requires-Dist: langchain-core (>=0.3.47,<0.4.0)
Requires-Dist: mcp (>=1.4.1,<2.0.0)
Requires-Dist: openai-agents (>=0.0.6,<0.0.7)
Requires-Dist: rich (>=13.9.4,<14.0.0)
